{
    "members":[
    {
        "name": "Asante Solutions",
        "tagline": "Innovative Digital Marketing Solutions",
        "email": "contact@asantesolutions.com",
        "phone": "031-555-1234",
        "url": "https://asantesolutions.com",
        "image": "../images/asantesolutions.jpeg",
        "membership_level": "silver",
        "address": "56 Oakwood Drive, Durban Central"
    },
    {
        "name": "Seaside Coffee",
        "tagline": "Best Coffee in Town",
        "email": "info@seasidecoffee.com",
        "phone": "031-888-9876",
        "url": "https://seasidecoffee.com",
        "image": "../images/seasidecoffee.jpeg",
        "membership_level": "member",
        "address": "88 Rainbow Circle, Old Mill Road, Durban"
    },
    {
        "name": "Zen Spa",
        "tagline": "Experience of Relaxation",
        "email": "contact@zenspa.com",
        "phone": "031-222-4226",
        "url": "https://zenspa.com",
        "image": "../images/zenspa.jpeg",
        "membership_level": "gold",
        "address": "501 Peter Mokaba Road, Morningside, Durban"
    },
    {
        "name": "Elizabeth Gordon Gallery",
        "tagline": "KZN's premier commercial art gallery",
        "email": "joy@elizabethgordon.co.za",
        "phone": "031-03-8133",
        "url": "https://elizabethgordon.co.za/",
        "image": "../images/artgallery.jpeg",
        "membership_level": "member",
        "address": "148 Montpelier Rd, Durban"
    },
    {
        "name": "Madam & Sir",
        "tagline": "Savor the Art of Fine Dining Hospitality",
        "email": "Bookings@madamandsir.co.za",
        "phone": "031-816-6670",
        "url": "https://madamandsir.co.za",
        "image": "../images/madamandsir.jpeg",
        "membership_level": "gold",
        "address": "262 Florida Rd, Morningside, Durban, "
    },
    {
        "name": "Indoni Fashion House",
        "tagline": "",
        "email": "info@indonifashionhouse.com",
        "phone": "072-424-0161",
        "url": "https://indonifashionhouse.com/",
        "image": "../images/fashionhouse.jpeg",
        "membership_level": "silver",
        "address": "501 Peter Mokaba Road, Morningside, Durban"
    },
    {
        "name": "Lifestyle Gym",
        "tagline": "A functional fitness & lifestyle centre in Durban North",
        "email": "join@lifestylegym.com",
        "phone": "063-870-8958",
        "url": "https://lifestylegym.co.za/",
        "image": "../images/lifestylegym.jpeg",
        "membership_level": "member",
        "address": "181 Lothian Road, Durban North"
    }
]
}